odoo/addons/product_variant_sale_price/README.rst
odoo/addons/product_variant_sale_price/__init__.py
odoo/addons/product_variant_sale_price/__manifest__.py
odoo/addons/product_variant_sale_price/hooks.py
odoo/addons/product_variant_sale_price/i18n/ca.po
odoo/addons/product_variant_sale_price/i18n/de.po
odoo/addons/product_variant_sale_price/i18n/el_GR.po
odoo/addons/product_variant_sale_price/i18n/es.po
odoo/addons/product_variant_sale_price/i18n/es_ES.po
odoo/addons/product_variant_sale_price/i18n/es_MX.po
odoo/addons/product_variant_sale_price/i18n/eu.po
odoo/addons/product_variant_sale_price/i18n/fi.po
odoo/addons/product_variant_sale_price/i18n/fr.po
odoo/addons/product_variant_sale_price/i18n/fr_CH.po
odoo/addons/product_variant_sale_price/i18n/fr_FR.po
odoo/addons/product_variant_sale_price/i18n/gl.po
odoo/addons/product_variant_sale_price/i18n/hr.po
odoo/addons/product_variant_sale_price/i18n/hr_HR.po
odoo/addons/product_variant_sale_price/i18n/it.po
odoo/addons/product_variant_sale_price/i18n/nl.po
odoo/addons/product_variant_sale_price/i18n/nl_NL.po
odoo/addons/product_variant_sale_price/i18n/product_variant_sale_price.pot
odoo/addons/product_variant_sale_price/i18n/pt.po
odoo/addons/product_variant_sale_price/i18n/pt_BR.po
odoo/addons/product_variant_sale_price/i18n/ro.po
odoo/addons/product_variant_sale_price/i18n/ru.po
odoo/addons/product_variant_sale_price/i18n/sk.po
odoo/addons/product_variant_sale_price/i18n/sl.po
odoo/addons/product_variant_sale_price/i18n/tr.po
odoo/addons/product_variant_sale_price/i18n/tr_TR.po
odoo/addons/product_variant_sale_price/i18n/vi_VN.po
odoo/addons/product_variant_sale_price/i18n/zh_CN.po
odoo/addons/product_variant_sale_price/models/__init__.py
odoo/addons/product_variant_sale_price/models/product_product.py
odoo/addons/product_variant_sale_price/models/product_template.py
odoo/addons/product_variant_sale_price/readme/CONTRIBUTORS.md
odoo/addons/product_variant_sale_price/readme/DESCRIPTION.md
odoo_addon_product_variant_sale_price-18.0.1.0.1.1.dist-info/METADATA
odoo_addon_product_variant_sale_price-18.0.1.0.1.1.dist-info/WHEEL
odoo_addon_product_variant_sale_price-18.0.1.0.1.1.dist-info/top_level.txt
odoo_addon_product_variant_sale_price-18.0.1.0.1.1.dist-info/RECORD
